astir/__init__.py
astir/astir.py
astir/data/__init__.py
astir/data/data_readers.py
astir/data/scdataset.py
astir/models/__init__.py
astir/models/abstract.py
astir/models/cellstate.py
astir/models/cellstate_recognet.py
astir/models/celltype.py
astir/models/celltype_recognet.py
astir-0.1.5.data/scripts/astir
tests/__init__.py
tests/conftest.py
tests/test_astir.py
tests/test_bin_astir.py
tests/test_code_smell.py
tests/test_notebooks.py
tests/models/__init__.py
tests/models/test_cellstate.py
tests/models/test_celltype.py
tests/models/test_scdataset.py
astir-0.1.5.dist-info/LICENSE
astir-0.1.5.dist-info/METADATA
astir-0.1.5.dist-info/WHEEL
astir-0.1.5.dist-info/top_level.txt
astir-0.1.5.dist-info/RECORD
