Metadata-Version: 2.1
Name: astir
Version: 0.1.5
Summary: 
Home-page: https://github.com/camlab-bioml/astir
Author: Jinyu Hou, Sunyun Lee, Michael Geuenich, Kieran Campbell
Author-email: kierancampbell@lunenfeld.ca
License: GPLv2
Project-URL: Documentation, https://astir.readthedocs.io/en/latest/
Project-URL: Source Code, https://github.com/camlab-bioml/astir
Classifier: Programming Language :: Python :: 3
Classifier: License :: OSI Approved :: GNU General Public License v2 (GPLv2)
Classifier: Operating System :: OS Independent
Classifier: Topic :: Scientific/Engineering :: Bio-Informatics
License-File: LICENSE
Requires-Dist: torch
Requires-Dist: pandas
Requires-Dist: numpy
Requires-Dist: nbformat
Requires-Dist: pyyaml
Requires-Dist: scikit-learn
Requires-Dist: argparse
Requires-Dist: matplotlib
Requires-Dist: loompy
Requires-Dist: tqdm
Requires-Dist: anndata
Requires-Dist: rootpath
Requires-Dist: nbconvert
Requires-Dist: seaborn
Requires-Dist: jupyter-client
Requires-Dist: ipykernel
Requires-Dist: ipython
Requires-Dist: h5py
Requires-Dist: FlowCytometryTools
Requires-Dist: fastcluster
Requires-Dist: sphinx
Requires-Dist: sphinx-autodoc-typehints
Requires-Dist: sphinx-rtd-theme
Requires-Dist: autodocsumm
Requires-Dist: nbsphinx
Requires-Dist: nbsphinx-link
Requires-Dist: tables
Requires-Dist: typeguard
Requires-Dist: mypy
